stateless/__init__.py
stateless/ability.py
stateless/async_.py
stateless/console.py
stateless/effect.py
stateless/errors.py
stateless/files.py
stateless/functions.py
stateless/handler.py
stateless/need.py
stateless/py.typed
stateless/schedule.py
stateless/time.py
stateless-0.6.1.dist-info/METADATA
stateless-0.6.1.dist-info/WHEEL
stateless-0.6.1.dist-info/licenses/LICENSE
stateless-0.6.1.dist-info/RECORD
