Metadata-Version: 2.4
Name: stateless
Version: 0.6.1
Summary: Statically typed, purely functional effects for Python
Author-email: suned <sd@dybro-debel.dk>
License-File: LICENSE
Requires-Python: >=3.10
Requires-Dist: cloudpickle<4,>=3.0.0
Requires-Dist: typing-extensions<5,>=4.8.0
